INSTALL.md
LICENSE.md
MANIFEST.in
README.md
setup.py
bin/bt
blogtool/__init__.py
blogtool/__main__.py
blogtool/__version__.py
blogtool/fileprocessor.py
blogtool/headerparse.py
blogtool/html2md.py
blogtool/options.py
blogtool/utils.py
blogtool.egg-info/PKG-INFO
blogtool.egg-info/SOURCES.txt
blogtool.egg-info/dependency_links.txt
blogtool.egg-info/not-zip-safe
blogtool.egg-info/requires.txt
blogtool.egg-info/top_level.txt
blogtool/xmlproxy/__init__.py
blogtool/xmlproxy/proxybase.py
blogtool/xmlproxy/wp_proxy.py