Metadata-Version: 1.0
Name: blogtool
Version: 1.1.2
Summary: A command-line, XMLRPC based blog client
Home-page: https://github.com/lama7/blogtool
Author: Gerry LaMontagne
Author-email: gjlama94 [at] gmail [dot] com
License: MIT
Download-URL: https://pypi.python.org/packages/source/b/blogtool/blogtool-1.1.2.tar.gz
Platform: UNKNOWN
Classifier: Development Status :: 5 - Production/Stable
Classifier: Environment :: Console
Classifier: License :: OSI Approved :: MIT License
Classifier: Intended Audience :: End Users/Desktop
Classifier: Operating System :: POSIX :: Linux
Classifier: Programming Language :: Python :: 2.6
Classifier: Programming Language :: Python :: 2.7
Classifier: Topic :: Internet :: WWW/HTTP :: Site Management
Classifier: Topic :: Text Processing
Classifier: Topic :: Utilities
